__init__.py
rembus/__init__.py
rembus/core.py
rembus/protocol.py
rembus/settings.py
rembus/sync.py
rembus-0.5.0.dist-info/licenses/LICENSE
rembus-0.5.0.dist-info/METADATA
rembus-0.5.0.dist-info/WHEEL
rembus-0.5.0.dist-info/top_level.txt
rembus-0.5.0.dist-info/RECORD
