Metadata-Version: 2.4
Name: rembus
Version: 0.5.0
Summary: Rembus for python
Author-email: Attilio Donà <attilio.dona@gmail.com>
License-Expression: AGPL-3.0-only
Project-URL: Homepage, https://github.com/cardo-org/rembus.python
Project-URL: Bug Tracker, https://github.com/cardo-org/rembus.python/issues
Keywords: rembus,rpc,publish,subscribe,websocket,cbor
Classifier: Programming Language :: Python :: 3
Classifier: Operating System :: OS Independent
Classifier: Development Status :: 4 - Beta
Requires-Python: >=3.12
License-File: LICENSE
Requires-Dist: async-timeout
Requires-Dist: platformdirs
Requires-Dist: pandas
Requires-Dist: pyarrow
Requires-Dist: websockets
Requires-Dist: cbor2
Requires-Dist: cryptography
Requires-Dist: narwhals
Requires-Dist: polars
Requires-Dist: pydantic
Provides-Extra: dev
Requires-Dist: check-manifest; extra == "dev"
Requires-Dist: bumpver; extra == "dev"
Requires-Dist: twine; extra == "dev"
Provides-Extra: test
Requires-Dist: coverage; extra == "test"
Requires-Dist: mock; extra == "test"
Requires-Dist: pytest; extra == "test"
Requires-Dist: pytest-asyncio; extra == "test"
Requires-Dist: pytest-mock; extra == "test"
Requires-Dist: pytest-cov; extra == "test"
Dynamic: license-file
